lsst/cbptimer/__init__.py
lsst/cbptimer/main.py
lsst_cbptimer-0.0.1.dist-info/LICENSE
lsst_cbptimer-0.0.1.dist-info/METADATA
lsst_cbptimer-0.0.1.dist-info/WHEEL
lsst_cbptimer-0.0.1.dist-info/entry_points.txt
lsst_cbptimer-0.0.1.dist-info/top_level.txt
lsst_cbptimer-0.0.1.dist-info/RECORD
