Metadata-Version: 2.1
Name: lsst-cbptimer
Version: 0.0.1
Summary: Command line tool for Rubin Observatory CBP calibration system logic timers
Author-email: Fritz Mueller <fritzm@slac.stanford.edu>
Maintainer-email: Fritz Mueller <fritzm@slac.stanford.edu>
License: MIT License
Project-URL: Homepage, https://github.com/lsst-sitcom/cbptimer
Project-URL: Documentation, https://github.com/lsst-sitcom/cbptimer/blob/master/README.md
Project-URL: Repository, https://github.com/lsst-sitcom/cbptimer
Keywords: Rubin,Rubin Observatory,LSST,CBP
Classifier: Development Status :: 3 - Alpha
Classifier: Environment :: Console
Classifier: Intended Audience :: Science/Research
Classifier: License :: OSI Approved :: MIT License
Classifier: Natural Language :: English
Classifier: Operating System :: POSIX :: Linux
Classifier: Programming Language :: Python :: 3
Classifier: Programming Language :: Python :: 3.9
Classifier: Programming Language :: Python :: 3.10
Classifier: Programming Language :: Python :: 3.11
Classifier: Programming Language :: Python :: 3.12
Classifier: Topic :: Scientific/Engineering
Classifier: Topic :: Scientific/Engineering :: Astronomy
Classifier: Topic :: System :: Hardware
Classifier: Typing :: Typed
Requires-Python: >=3.9
License-File: LICENSE
Requires-Dist: pigpio
Provides-Extra: dev
Requires-Dist: build ; extra == 'dev'
Requires-Dist: mypy ; extra == 'dev'
Requires-Dist: ruff ; extra == 'dev'
Requires-Dist: twine ; extra == 'dev'
